{
  "evidence_id": "STUDIO-DEFAULT-CREDENTIAL-PROMPT-MOBILE-COMPACT-VERIFIED-20260622",
  "round_id": "GPCF-UI-STUDIO-WORKBENCH-011",
  "target": {
    "project": "Studio",
    "surface": "ai-chat",
    "component": "/Users/lujunxiang/Projects/GlobalCloud V0.0.1/GlobalCloud Studio/packages/client/src/components/auth/DefaultCredentialPrompt.vue"
  },
  "ui_gate_status": "ui_partial",
  "status_ceiling": "ui_evidence_candidate",
  "tools_used": [
    "manual",
    "vitest",
    "safaridriver"
  ],
  "tools_unavailable_or_not_invoked": [
    "impeccable_not_invoked",
    "figma_not_verified"
  ],
  "implementation": {
    "logic_changed": false,
    "mobile_layout_compacted": true,
    "desktop_layout_preserved": true,
    "shared_scope_only": true
  },
  "verification": {
    "unit_test_command": "npm test -- tests/client/default-credential-prompt.test.ts",
    "unit_test_passed": true,
    "runtime_browser": "Safari WebDriver",
    "mobile_prompt_visible": true,
    "mobile_sidebar_visible_with_prompt": true,
    "mobile_prompt_width": 312,
    "mobile_prompt_height": 169,
    "mobile_prompt_right_gap": 8,
    "mobile_prompt_bottom_gap": 8
  },
  "screenshots": {
    "mobile_prompt_compact": "docs/harness/evidence/assets/studio-default-credential-prompt-mobile-compact-20260622.png"
  },
  "gates": {
    "G1": "pass",
    "G2": "pass",
    "G3": "partial",
    "G4": "pass",
    "G5": "not_applicable",
    "G6": "partial",
    "G7": "pass",
    "G8": "pass",
    "G9": "pass"
  },
  "findings": [
    "The mobile prompt is now compacted to a 312x169 floating card anchored 8px from the right and bottom edges.",
    "The mobile sidebar remains visible and usable while the prompt is present.",
    "The change is style-only and does not alter dismissal or account-settings actions."
  ],
  "non_claims": [
    "does not prove default credential governance closure",
    "does not remove the prompt entirely",
    "does not grant accepted, integrated, or production_ready status"
  ]
}
