{
  "id": "gckf-p0-physical-data-model-schema-dry-run-v0.1",
  "description": "GC-Knowledge Fabric P0-D9 physical data model schema dry-run. It parses the local schema draft only and does not execute migrations, connect to a database, or write production data.",
  "version": "v0.1",
  "schemaPath": "packages/api/src/kds/v2/schema.sql",
  "requiredTables": [
    "knowledge_objects",
    "knowledge_sources",
    "knowledge_evidence",
    "object_pool_bindings",
    "fact_candidates",
    "sop_candidates",
    "writeback_candidates",
    "knowledge_events",
    "knowledge_acl",
    "knowledge_embeddings",
    "knowledge_index_jobs",
    "kds_pools",
    "waes_gate_results",
    "waes_gate_policies",
    "kwe_work_items",
    "kwe_workpacks",
    "gap_records",
    "bounty_records",
    "confirmation_records",
    "committee_records",
    "dispute_records",
    "contribution_records",
    "revenue_records",
    "quota_records",
    "decision_records",
    "loop_records",
    "harness_evidence_records",
    "capability_invocations",
    "agent_used_knowledge",
    "okf_policy_versions"
  ],
  "tableGroups": {
    "kds_core": ["knowledge_objects", "knowledge_sources", "knowledge_evidence", "knowledge_events"],
    "kds_index_acl": ["knowledge_acl", "knowledge_embeddings", "knowledge_index_jobs", "kds_pools", "object_pool_bindings"],
    "candidate": ["fact_candidates", "sop_candidates", "writeback_candidates"],
    "waes": ["waes_gate_results", "waes_gate_policies"],
    "kwe": ["kwe_work_items", "kwe_workpacks", "gap_records", "bounty_records", "confirmation_records"],
    "governance": ["committee_records", "dispute_records", "decision_records", "loop_records", "harness_evidence_records", "okf_policy_versions"],
    "ledger": ["contribution_records", "revenue_records", "quota_records"],
    "mmc_agent": ["capability_invocations", "agent_used_knowledge"]
  },
  "forbiddenSql": ["DROP TABLE", "ALTER TABLE", "INSERT INTO", "UPDATE ", "DELETE FROM", "TRUNCATE"],
  "forbiddenExecution": {
    "runsMigration": 0,
    "connectsDatabase": 0,
    "writesKds": 0,
    "writesWaes": 0,
    "writesKwe": 0,
    "writesBusinessSystem": 0,
    "writesRevenueDistribution": 0,
    "writesExternalApi": 0
  },
  "expectedSummary": {
    "tableCount": 30,
    "tableGroupCount": 8,
    "tablesWithPrimaryKey": 30,
    "tablesWithTenantId": 30,
    "forbiddenSqlMatches": 0,
    "runsMigration": 0,
    "connectsDatabase": 0,
    "writesKds": 0,
    "writesWaes": 0,
    "writesKwe": 0,
    "writesBusinessSystem": 0,
    "writesRevenueDistribution": 0,
    "writesExternalApi": 0,
    "noWrite": true
  }
}
